faicons/__init__.py
faicons/_core.py
faicons/icons.json
faicons/py.typed
faicons-0.2.2.dist-info/LICENSE
faicons-0.2.2.dist-info/METADATA
faicons-0.2.2.dist-info/WHEEL
faicons-0.2.2.dist-info/top_level.txt
faicons-0.2.2.dist-info/RECORD
