Metadata-Version: 2.1
Name: faicons
Version: 0.2.2
Summary: An interface to Font-Awesome for use in Shiny.
Home-page: https://github.com/rstudio/py-faicons
Author: Carson Sievert
Author-email: carson@rstudio.com
License: MIT
Project-URL: Bug Tracker, https://github.com/rstudio/py-faicons/issues
Project-URL: Source Code, https://github.com/rstudio/py-faicons
Keywords: fontawesome
Platform: any
Classifier: Development Status :: 2 - Pre-Alpha
Classifier: Intended Audience :: Developers
Classifier: License :: OSI Approved :: MIT License
Classifier: Programming Language :: Python
Classifier: Programming Language :: Python :: 3.8
Classifier: Programming Language :: Python :: 3.9
Classifier: Programming Language :: Python :: 3.10
Classifier: Programming Language :: Python :: 3.11
Classifier: Topic :: Text Processing :: Markup :: HTML
Requires-Python: >=3.8
Provides-Extra: test
Provides-Extra: dev
